[
    {
        "value": "Caribbean"
    },
    {
        "value": "Mexico"
    },
    {
        "value": "Bahamas"
    },
    {
        "value": "Alaska"
    },
    {
        "value": "Europe"
    },
    {
        "value": "Hawaii"
    },
    {
        "value": "Bermuda"
    },
    {
        "value": "Canada/New England/NY"
    },
    {
        "value": "River Cruises"
    },
    {
        "value": "Any value"
    },
    {
        "value": "Alaska - All"
    },
    {
        "value": "Alaska - Gulf of Alaska"
    },
    {
        "value": "Alaska - Inside Passage"
    },
    {
        "value": "Antarctica"
    },
    {
        "value": "Australia/New Zealand"
    },
    {
        "value": "Caribbean - All"
    },
    {
        "value": "Caribbean - Eastern"
    },
    {
        "value": "Caribbean - Southern"
    },
    {
        "value": "Caribbean - Western"
    },
    {
        "value": "Europe - All"
    },
    {
        "value": "Europe - E. Mediterranean"
    },
    {
        "value": "Europe - Mediterranean - All"
    },
    {
        "value": "Europe - Northern"
    },
    {
        "value": "Europe - W. Mediterranean"
    },
    {
        "value": "Europe - Western"
    },
    {
        "value": "Exotic - Asia/Africa/Other"
    },
    {
        "value": "Galapagos"
    },
    {
        "value": "Pacific Coast"
    },
    {
        "value": "Panama Canal/C. America"
    },
    {
        "value": "River Cruises - All"
    },
    {
        "value": "River Cruises - China/Asia"
    },
    {
        "value": "River Cruises - Egypt/Africa"
    },
    {
        "value": "River Cruises - Europe"
    },
    {
        "value": "River Cruises - South America"
    },
    {
        "value": "River Cruises - United States"
    },
    {
        "value": "South America"
    },
    {
        "value": "South Pacific - All"
    },
    {
        "value": "South Pacific - Tahiti"
    },
    {
        "value": "Transatlantic"
    },
    {
        "value": "Transpacific"
    },
    {
        "value": "U.S. - All"
    },
    {
        "value": "World Cruise"
    }
]